{
  "metaTitle": "| Reskyt",
  "description": "",
  "title": "Douglas Portugal ya dispone de su App",
  "date": {
    "day": 7,
    "month": 10,
    "year": 2021
  },
  "readTime": 3,
  "image": "/images/blog/douglas-portugal-ya-dispone-de-su-app.jpeg",
  "html": "<p><strong>Perfumería Douglas: ¡descubre la tienda online!<br></strong><br><strong>Ahora también en App</strong><br><br>¡Bienvenido al mundo de la belleza y el cuidado! Douglas.pt es una perfumería en línea llena de una amplia selección de productos que le permiten descubrir su belleza y estilo natural. En la perfumería Douglas puedes aventurarte a explorar las últimas novedades o redescubrir clásicos en perfumes, maquillaje y cosmética.</p>"
}